{"details":[{"title":"\u0caa\u0ccd\u0cb0\u0ca4\u0cbf\u0cad\u0c9f\u0ca8\u0cc6\u0c97\u0cc6 \u0c92\u0c95\u0ccd\u0c95\u0cb2\u0cbf\u0c97 \u0cb8\u0c82\u0c98\u0ca6 \u0cac\u0cc6\u0c82\u0cac\u0cb2","content":"<blockquote class=\"twitter-tweet\">\n<p lang=\"in\" dir=\"ltr\">Karnataka: Members of the Vokkaliga Sangha protest in Bengaluru against Congress leader DK Shivakumar's arrest by Enforcement Directorate (ED). Shivakumar belongs to the Vokkaliga community. <a href=\"https:\/\/t.co\/lPH9t0YP7U\">pic.twitter.com\/lPH9t0YP7U<\/a><\/p>\n\u2014 ANI (@ANI) <a href=\"https:\/\/twitter.com\/ANI\/status\/1171666542347661312?ref_src=twsrc%5Etfw\">September 11, 2019<\/a><\/blockquote> <script async src=\"https:\/\/platform.twitter.com\/widgets.js\" charset=\"utf-8\"><\/script>","date":"2019-09-11 12:23:19","pin":"0","status":"1"},{"title":"","content":"<p><span style=\"color: rgb(255, 0, 0);\"><strong>\u0c95\u0cc7\u0c82\u0ca6\u0ccd\u0cb0 \u0cb8\u0cb0\u0ccd\u0c95\u0cbe\u0cb0\u0ca6 \u0cb8\u0cc7\u0ca1\u0cbf\u0ca8 \u0cb0\u0cbe\u0c9c\u0c95\u0cbe\u0cb0\u0ca3 \u0cb8\u0cb9\u0cbf\u0cb8\u0cb2\u0cb8\u0cbe\u0ca7\u0ccd\u0caf: \u0c95\u0cc6\u0caa\u0cbf\u0cb8\u0cbf\u0cb8\u0cbf \u0c85\u0ca7\u0ccd\u0caf\u0c95\u0ccd\u0cb7 \u0ca6\u0cbf\u0ca8\u0cc7\u0cb6\u0ccd \u0c97\u0cc1\u0c82\u0ca1\u0cc2\u0cb0\u0cbe\u0cb5\u0ccd<\/strong><\/span><\/p>\n<p><span style=\"color: rgb(255, 0, 0);\"><strong> <\/strong><\/span>\u0c95\u0cbe\u0c82\u0c97\u0ccd\u0cb0\u0cc6\u0cb8\u0ccd \u0cb8\u0c9a\u0cbf\u0cb5 \u0ca1\u0cbf\u0c95\u0cc6 \u0cb6\u0cbf\u0cb5\u0c95\u0cc1\u0cae\u0cbe\u0cb0\u0ccd \u0cb0\u0ca8\u0ccd\u0ca8\u0cc1 \u0cac\u0c82\u0ca7\u0cbf\u0cb8\u0cc1\u0cb5 \u0cae\u0cc2\u0cb2\u0c95 \u0c95\u0cc7\u0c82\u0ca6\u0ccd\u0cb0 \u0cb8\u0cb0\u0ccd\u0c95\u0cbe\u0cb0 \u0cb8\u0cc7\u0ca1\u0cbf\u0ca8 \u0cb0\u0cbe\u0c9c\u0c95\u0cbe\u0cb0\u0ca3 \u0cae\u0cbe\u0ca1\u0cc1\u0ca4\u0ccd\u0ca4\u0cbf\u0ca6\u0ccd\u0ca6\u0cc1, \u0c95\u0cc7\u0c82\u0ca6\u0ccd\u0cb0\u0ca6 \u0cae\u0ccb\u0ca6\u0cbf \u0cb8\u0cb0\u0ccd\u0c95\u0cbe\u0cb0\u0ca6 \u0c88 \u0c95\u0ccd\u0cb0\u0cae\u0cb5\u0ca8\u0ccd\u0ca8\u0cc1 \u0cb0\u0cbe\u0c9c\u0ccd\u0caf\u0ca6 \u0c9c\u0ca8\u0cb0\u0cc1 \u0cb8\u0cb9\u0cbf\u0cb8\u0cc1\u0cb5\u0cc1\u0ca6\u0cbf\u0cb2\u0ccd\u0cb2 \u0c8e\u0c82\u0ca6\u0cc1 \u0c95\u0cc6\u0caa\u0cbf\u0cb8\u0cbf\u0cb8\u0cbf \u0c85\u0ca7\u0ccd\u0caf\u0c95\u0ccd\u0cb7 \u0ca6\u0cbf\u0ca8\u0cc7\u0cb6\u0ccd \u0c97\u0cc1\u0c82\u0ca1\u0cc2\u0cb0\u0cbe\u0cb5\u0ccd \u0cb9\u0cc7\u0cb3\u0cbf\u0ca6\u0ccd\u0ca6\u0cbe\u0cb0\u0cc6.<\/p>\n<p>\u0cac\u0cc6\u0c82\u0c97\u0cb3\u0cc2\u0cb0\u0cbf\u0ca8\u0cb2\u0ccd\u0cb2\u0cbf \u0ca8\u0ca1\u0cc6\u0caf\u0cc1\u0ca4\u0ccd\u0ca4\u0cbf\u0cb0\u0cc1\u0cb5 \u0ca1\u0cbf\u0c95\u0cc6\u0cb6\u0cbf \u0cac\u0c82\u0ca7\u0ca8 \u0cb5\u0cbf\u0cb0\u0ccb\u0ca7\u0cbf\u0cb8\u0cbf \u0caa\u0ccd\u0cb0\u0ca4\u0cbf\u0cad\u0c9f\u0ca8\u0cc6\u0caf\u0cb2\u0ccd\u0cb2\u0cbf \u0caa\u0cbe\u0cb2\u0ccd\u0c97\u0cca\u0c82\u0ca1\u0cc1 \u0ca8\u0cc6\u0cb0\u0cc6\u0ca6\u0cbf\u0ca6\u0ccd\u0ca6 \u0c95\u0cbe\u0cb0\u0ccd\u0caf\u0c95\u0cb0\u0ccd\u0ca4\u0cb0\u0ca8\u0ccd\u0ca8\u0cc1 \u0c89\u0ca6\u0ccd\u0ca6\u0cc7\u0cb6\u0cbf\u0cb8\u0cbf \u0cae\u0cbe\u0ca4\u0ca8\u0cbe\u0ca1\u0cbf\u0ca6 \u0c97\u0cc1\u0c82\u0ca1\u0cc2\u0cb0\u0cbe\u0cb5\u0ccd \u0c85\u0cb5\u0cb0\u0cc1, '\u0c95\u0cc7\u0c82\u0ca6\u0ccd\u0cb0 \u0cb8\u0cb0\u0ccd\u0c95\u0cbe\u0cb0 \u0ca6\u0ccd\u0cb5\u0cc7\u0cb7\u0ca6 \u0cb0\u0cbe\u0c9c\u0c95\u0cbe\u0cb0\u0ca3 \u0cae\u0cbe\u0ca1\u0cac\u0cbe\u0cb0\u0ca6\u0cc1 \u0c8e\u0c82\u0cac \u0cb8\u0c82\u0ca6\u0cc7\u0cb6 \u0cac\u0cc3\u0cb9\u0ca4\u0ccd \u0c9c\u0ca8\u0cb8\u0cae\u0cc2\u0cb9\u0ca6 \u0cae\u0cc2\u0cb2\u0c95 \u0cb5\u0ccd\u0caf\u0c95\u0ccd\u0ca4\u0cb5\u0cbe\u0c97\u0cbf\u0ca6\u0cc6.  \u0c87\u0cb2\u0ccd\u0cb2\u0cbf \u0c87\u0c82\u0ca6\u0cc1 50 \u0cb8\u0cbe\u0cb5\u0cbf\u0cb0\u0ca6\u0cb7\u0ccd\u0ca1\u0cc1 \u0c9c\u0ca8 \u0cb8\u0cc7\u0cb0\u0cb2\u0cbf\u0ca6\u0ccd\u0ca6\u0cc1, \u0c87\u0ca6\u0cc1 \u0c95\u0cc7\u0c82\u0ca6\u0ccd\u0cb0\u0c95\u0ccd\u0c95\u0cc6 \u0ca8\u0cc0\u0ca1\u0cc1\u0cb5 \u0caa\u0ccd\u0cb0\u0ca4\u0ccd\u0caf\u0cc1\u0ca4\u0ccd\u0ca4\u0cb0 \u0c8e\u0c82\u0ca6\u0cb0\u0cc1. \u0c85\u0c82\u0ca4\u0cc6\u0caf\u0cc7 \u0c95\u0cc7\u0c82\u0ca6\u0ccd\u0cb0 \u0cb8\u0cb0\u0ccd\u0c95\u0cbe\u0cb0 \u0c90\u0c9f\u0cbf. \u0c87\u0ca1\u0cbf \u0c87\u0cb2\u0cbe\u0c96\u0cc6 \u0c97\u0cb3\u0ca8\u0ccd\u0ca8\u0cc1 \u0ca6\u0cc1\u0cb0\u0ccd\u0cac\u0cb3\u0c95\u0cc6 \u0cae\u0cbe\u0ca1\u0cc1\u0cb5\u0cc1\u0ca6\u0cc1 \u0caa\u0ccd\u0cb0\u0c9c\u0cbe\u0caa\u0ccd\u0cb0\u0cad\u0cc1\u0ca4\u0ccd\u0cb5\u0c95\u0ccd\u0c95\u0cc6 \u0c85\u0caa\u0cbe\u0caf\u0c95\u0cbe\u0cb0\u0cbf. \u0ca1\u0cbf\u0c95\u0cc6\u0cb6\u0cbf \u0c85\u0cb5\u0cb0\u0cc1 \u0ca4\u0ca8\u0cbf\u0c96\u0cc6\u0c97\u0cc6 \u0cb8\u0cb9\u0c95\u0cbe\u0cb0 \u0ca8\u0cc0\u0ca1\u0cbf\u0ca6 \u0cae\u0cc7\u0cb2\u0cc2 \u0c85\u0cb5\u0cb0\u0cbf\u0c97\u0cc6 \u0c95\u0cbf\u0cb0\u0cc1\u0c95\u0cc1\u0cb3 \u0ca8\u0cc0\u0ca1\u0cc1\u0cb5 \u0cb8\u0cb2\u0cc1\u0cb5\u0cbe\u0c97\u0cbf\u0caf\u0cc7 \u0c85\u0cb5\u0cb0\u0ca8\u0ccd\u0ca8\u0cc1 \u0cac\u0c82\u0ca7\u0cbf\u0cb8\u0cb2\u0cbe\u0c97\u0cbf\u0ca6\u0cc6 \u0c8e\u0c82\u0ca6\u0cc1 \u0cb9\u0cc7\u0cb3\u0cbf\u0ca6\u0cb0\u0cc1.<\/p>\n<p>\u0c87\u0ca6\u0cc7 \u0cb5\u0cc7\u0cb3\u0cc6 \u0cb5\u0cbf\u0c9c\u0caf\u0ccd \u0cae\u0cb2\u0ccd\u0caf, \u0ca8\u0cc0\u0cb0\u0cb5\u0ccd \u0cae\u0ccb\u0ca6\u0cbf \u0caa\u0ccd\u0cb0\u0c95\u0cb0\u0ca3\u0cb5\u0ca8\u0ccd\u0ca8\u0cc1 \u0caa\u0ccd\u0cb0\u0cb8\u0ccd\u0ca4\u0cbe\u0caa\u0cbf\u0cb8\u0cbf\u0ca6 \u0c97\u0cc1\u0c82\u0ca1\u0cc2\u0cb0\u0cbe\u0cb5\u0ccd \u0c85\u0cb5\u0cb0\u0cc1, '3 \u0ca4\u0cbf\u0c82\u0c97\u0cb3\u0cb2\u0ccd\u0cb2\u0cbf \u0cac\u0ccd\u0caf\u0cbe\u0c82\u0c95\u0cc1\u0c97\u0cb3\u0cbf\u0c82\u0ca6 32 \u0cb8\u0cbe\u0cb5\u0cbf\u0cb0 \u0c95\u0ccb\u0c9f\u0cbf \u0cb2\u0cc2\u0c9f\u0cbf\u0caf\u0cbe\u0c97\u0cbf\u0ca6\u0cc6. \u0c85\u0ca6\u0ca8\u0ccd\u0ca8\u0cc1 \u0ca4\u0ca1\u0cc6\u0caf\u0cb2\u0cc1 \u0c8f\u0ca8\u0cc1 \u0c95\u0ccd\u0cb0\u0cae \u0c95\u0cc8\u0c97\u0cca\u0c82\u0ca1\u0cbf\u0ca6\u0ccd\u0ca6\u0cc0\u0cb0\u0cbf \u0c8e\u0c82\u0ca6\u0cc1 \u0c85\u0cb5\u0cb0\u0cc1 \u0caa\u0ccd\u0cb0\u0cb6\u0ccd\u0ca8\u0cbf\u0cb8\u0cbf\u0ca6\u0cb0\u0cc1. \u0cb5\u0cbf\u0cb0\u0ccb\u0ca7 \u0caa\u0c95\u0ccd\u0cb7\u0ca6\u0cb5\u0cb0\u0ca8\u0ccd\u0ca8\u0cc1 \u0cae\u0cc1\u0c97\u0cbf\u0cb8\u0cc1\u0cb5 \u0ca4\u0c82\u0ca4\u0ccd\u0cb0\u0cb5\u0ca8\u0ccd\u0ca8\u0cc1 \u0cb8\u0cb9\u0cbf\u0cb8\u0cb2\u0cc1 \u0cb8\u0cbe\u0ca7\u0ccd\u0caf\u0cb5\u0cbf\u0cb2\u0ccd\u0cb2. \u0c9c\u0ca8 \u0c87\u0ca6\u0cb0 \u0cb5\u0cbf\u0cb0\u0cc1\u0ca6\u0ccd\u0ca7 \u0c8e\u0ca6\u0ccd\u0ca6\u0cc1 \u0ca8\u0cbf\u0c82\u0ca4\u0cbf\u0ca6\u0ccd\u0ca6\u0cbe\u0cb0\u0cc6. \u0c87\u0ca6\u0ca8\u0ccd\u0ca8\u0cc1 \u0c95\u0cc7\u0c82\u0ca6\u0ccd\u0cb0\u0c95\u0ccd\u0c95\u0cc6 \u0ca4\u0ca1\u0cc6\u0caf\u0cb2\u0cc1 \u0cb8\u0cbe\u0ca7\u0ccd\u0caf\u0cb5\u0cbf\u0cb2\u0ccd\u0cb2 \u0c8e\u0c82\u0ca6\u0cb0\u0cc1.<\/p>\n<p><img src=\"http:\/\/cms.newindianexpress.com\/FCKeditor\/fckeditor_img\/DKS01.jpg\" alt=\"\" \/><\/p>","date":"2019-09-11 12:46:04","pin":"0","status":"0"},{"title":"\u0c95\u0cc7\u0c82\u0ca6\u0ccd\u0cb0 \u0cb8\u0cb0\u0ccd\u0c95\u0cbe\u0cb0\u0ca6 \u0cb8\u0cc7\u0ca1\u0cbf\u0ca8 \u0cb0\u0cbe\u0c9c\u0c95\u0cbe\u0cb0\u0ca3 \u0cb8\u0cb9\u0cbf\u0cb8\u0cb2\u0cb8\u0cbe\u0ca7\u0ccd\u0caf: \u0c95\u0cc6\u0caa\u0cbf\u0cb8\u0cbf\u0cb8\u0cbf \u0c85\u0ca7\u0ccd\u0caf\u0c95\u0ccd\u0cb7 \u0ca6\u0cbf\u0ca8\u0cc7\u0cb6\u0ccd \u0c97\u0cc1\u0c82\u0ca1\u0cc2\u0cb0\u0cbe\u0cb5\u0ccd","content":"<p>\u0c95\u0cbe\u0c82\u0c97\u0ccd\u0cb0\u0cc6\u0cb8\u0ccd \u0cb8\u0c9a\u0cbf\u0cb5 \u0ca1\u0cbf\u0c95\u0cc6 \u0cb6\u0cbf\u0cb5\u0c95\u0cc1\u0cae\u0cbe\u0cb0\u0ccd \u0cb0\u0ca8\u0ccd\u0ca8\u0cc1 \u0cac\u0c82\u0ca7\u0cbf\u0cb8\u0cc1\u0cb5 \u0cae\u0cc2\u0cb2\u0c95 \u0c95\u0cc7\u0c82\u0ca6\u0ccd\u0cb0 \u0cb8\u0cb0\u0ccd\u0c95\u0cbe\u0cb0 \u0cb8\u0cc7\u0ca1\u0cbf\u0ca8 \u0cb0\u0cbe\u0c9c\u0c95\u0cbe\u0cb0\u0ca3 \u0cae\u0cbe\u0ca1\u0cc1\u0ca4\u0ccd\u0ca4\u0cbf\u0ca6\u0ccd\u0ca6\u0cc1, \u0c95\u0cc7\u0c82\u0ca6\u0ccd\u0cb0\u0ca6 \u0cae\u0ccb\u0ca6\u0cbf \u0cb8\u0cb0\u0ccd\u0c95\u0cbe\u0cb0\u0ca6 \u0c88 \u0c95\u0ccd\u0cb0\u0cae\u0cb5\u0ca8\u0ccd\u0ca8\u0cc1 \u0cb0\u0cbe\u0c9c\u0ccd\u0caf\u0ca6 \u0c9c\u0ca8\u0cb0\u0cc1 \u0cb8\u0cb9\u0cbf\u0cb8\u0cc1\u0cb5\u0cc1\u0ca6\u0cbf\u0cb2\u0ccd\u0cb2 \u0c8e\u0c82\u0ca6\u0cc1 \u0c95\u0cc6\u0caa\u0cbf\u0cb8\u0cbf\u0cb8\u0cbf \u0c85\u0ca7\u0ccd\u0caf\u0c95\u0ccd\u0cb7 \u0ca6\u0cbf\u0ca8\u0cc7\u0cb6\u0ccd \u0c97\u0cc1\u0c82\u0ca1\u0cc2\u0cb0\u0cbe\u0cb5\u0ccd \u0cb9\u0cc7\u0cb3\u0cbf\u0ca6\u0ccd\u0ca6\u0cbe\u0cb0\u0cc6.<\/p>\n<p>\u00a0<\/p>\n<p>\u0cac\u0cc6\u0c82\u0c97\u0cb3\u0cc2\u0cb0\u0cbf\u0ca8\u0cb2\u0ccd\u0cb2\u0cbf \u0ca8\u0ca1\u0cc6\u0caf\u0cc1\u0ca4\u0ccd\u0ca4\u0cbf\u0cb0\u0cc1\u0cb5 \u0ca1\u0cbf\u0c95\u0cc6\u0cb6\u0cbf \u0cac\u0c82\u0ca7\u0ca8 \u0cb5\u0cbf\u0cb0\u0ccb\u0ca7\u0cbf\u0cb8\u0cbf \u0caa\u0ccd\u0cb0\u0ca4\u0cbf\u0cad\u0c9f\u0ca8\u0cc6\u0caf\u0cb2\u0ccd\u0cb2\u0cbf \u0caa\u0cbe\u0cb2\u0ccd\u0c97\u0cca\u0c82\u0ca1\u0cc1 \u0ca8\u0cc6\u0cb0\u0cc6\u0ca6\u0cbf\u0ca6\u0ccd\u0ca6 \u0c95\u0cbe\u0cb0\u0ccd\u0caf\u0c95\u0cb0\u0ccd\u0ca4\u0cb0\u0ca8\u0ccd\u0ca8\u0cc1 \u0c89\u0ca6\u0ccd\u0ca6\u0cc7\u0cb6\u0cbf\u0cb8\u0cbf \u0cae\u0cbe\u0ca4\u0ca8\u0cbe\u0ca1\u0cbf\u0ca6 \u0c97\u0cc1\u0c82\u0ca1\u0cc2\u0cb0\u0cbe\u0cb5\u0ccd \u0c85\u0cb5\u0cb0\u0cc1, '\u0c95\u0cc7\u0c82\u0ca6\u0ccd\u0cb0 \u0cb8\u0cb0\u0ccd\u0c95\u0cbe\u0cb0 \u0ca6\u0ccd\u0cb5\u0cc7\u0cb7\u0ca6 \u0cb0\u0cbe\u0c9c\u0c95\u0cbe\u0cb0\u0ca3 \u0cae\u0cbe\u0ca1\u0cac\u0cbe\u0cb0\u0ca6\u0cc1 \u0c8e\u0c82\u0cac \u0cb8\u0c82\u0ca6\u0cc7\u0cb6 \u0cac\u0cc3\u0cb9\u0ca4\u0ccd \u0c9c\u0ca8\u0cb8\u0cae\u0cc2\u0cb9\u0ca6 \u0cae\u0cc2\u0cb2\u0c95 \u0cb5\u0ccd\u0caf\u0c95\u0ccd\u0ca4\u0cb5\u0cbe\u0c97\u0cbf\u0ca6\u0cc6.  \u0c87\u0cb2\u0ccd\u0cb2\u0cbf \u0c87\u0c82\u0ca6\u0cc1 50 \u0cb8\u0cbe\u0cb5\u0cbf\u0cb0\u0ca6\u0cb7\u0ccd\u0ca1\u0cc1 \u0c9c\u0ca8 \u0cb8\u0cc7\u0cb0\u0cb2\u0cbf\u0ca6\u0ccd\u0ca6\u0cc1, \u0c87\u0ca6\u0cc1 \u0c95\u0cc7\u0c82\u0ca6\u0ccd\u0cb0\u0c95\u0ccd\u0c95\u0cc6 \u0ca8\u0cc0\u0ca1\u0cc1\u0cb5 \u0caa\u0ccd\u0cb0\u0ca4\u0ccd\u0caf\u0cc1\u0ca4\u0ccd\u0ca4\u0cb0 \u0c8e\u0c82\u0ca6\u0cb0\u0cc1. \u0c85\u0c82\u0ca4\u0cc6\u0caf\u0cc7 \u0c95\u0cc7\u0c82\u0ca6\u0ccd\u0cb0 \u0cb8\u0cb0\u0ccd\u0c95\u0cbe\u0cb0 \u0c90\u0c9f\u0cbf. \u0c87\u0ca1\u0cbf \u0c87\u0cb2\u0cbe\u0c96\u0cc6 \u0c97\u0cb3\u0ca8\u0ccd\u0ca8\u0cc1 \u0ca6\u0cc1\u0cb0\u0ccd\u0cac\u0cb3\u0c95\u0cc6 \u0cae\u0cbe\u0ca1\u0cc1\u0cb5\u0cc1\u0ca6\u0cc1 \u0caa\u0ccd\u0cb0\u0c9c\u0cbe\u0caa\u0ccd\u0cb0\u0cad\u0cc1\u0ca4\u0ccd\u0cb5\u0c95\u0ccd\u0c95\u0cc6 \u0c85\u0caa\u0cbe\u0caf\u0c95\u0cbe\u0cb0\u0cbf. \u0ca1\u0cbf\u0c95\u0cc6\u0cb6\u0cbf \u0c85\u0cb5\u0cb0\u0cc1 \u0ca4\u0ca8\u0cbf\u0c96\u0cc6\u0c97\u0cc6 \u0cb8\u0cb9\u0c95\u0cbe\u0cb0 \u0ca8\u0cc0\u0ca1\u0cbf\u0ca6 \u0cae\u0cc7\u0cb2\u0cc2 \u0c85\u0cb5\u0cb0\u0cbf\u0c97\u0cc6 \u0c95\u0cbf\u0cb0\u0cc1\u0c95\u0cc1\u0cb3 \u0ca8\u0cc0\u0ca1\u0cc1\u0cb5 \u0cb8\u0cb2\u0cc1\u0cb5\u0cbe\u0c97\u0cbf\u0caf\u0cc7 \u0c85\u0cb5\u0cb0\u0ca8\u0ccd\u0ca8\u0cc1 \u0cac\u0c82\u0ca7\u0cbf\u0cb8\u0cb2\u0cbe\u0c97\u0cbf\u0ca6\u0cc6 \u0c8e\u0c82\u0ca6\u0cc1 \u0cb9\u0cc7\u0cb3\u0cbf\u0ca6\u0cb0\u0cc1.<\/p>\n<p>\u0c87\u0ca6\u0cc7 \u0cb5\u0cc7\u0cb3\u0cc6 \u0cb5\u0cbf\u0c9c\u0caf\u0ccd \u0cae\u0cb2\u0ccd\u0caf, \u0ca8\u0cc0\u0cb0\u0cb5\u0ccd \u0cae\u0ccb\u0ca6\u0cbf \u0caa\u0ccd\u0cb0\u0c95\u0cb0\u0ca3\u0cb5\u0ca8\u0ccd\u0ca8\u0cc1 \u0caa\u0ccd\u0cb0\u0cb8\u0ccd\u0ca4\u0cbe\u0caa\u0cbf\u0cb8\u0cbf\u0ca6 \u0c97\u0cc1\u0c82\u0ca1\u0cc2\u0cb0\u0cbe\u0cb5\u0ccd \u0c85\u0cb5\u0cb0\u0cc1, '3 \u0ca4\u0cbf\u0c82\u0c97\u0cb3\u0cb2\u0ccd\u0cb2\u0cbf \u0cac\u0ccd\u0caf\u0cbe\u0c82\u0c95\u0cc1\u0c97\u0cb3\u0cbf\u0c82\u0ca6 32 \u0cb8\u0cbe\u0cb5\u0cbf\u0cb0 \u0c95\u0ccb\u0c9f\u0cbf \u0cb2\u0cc2\u0c9f\u0cbf\u0caf\u0cbe\u0c97\u0cbf\u0ca6\u0cc6. \u0c85\u0ca6\u0ca8\u0ccd\u0ca8\u0cc1 \u0ca4\u0ca1\u0cc6\u0caf\u0cb2\u0cc1 \u0c8f\u0ca8\u0cc1 \u0c95\u0ccd\u0cb0\u0cae \u0c95\u0cc8\u0c97\u0cca\u0c82\u0ca1\u0cbf\u0ca6\u0ccd\u0ca6\u0cc0\u0cb0\u0cbf \u0c8e\u0c82\u0ca6\u0cc1 \u0c85\u0cb5\u0cb0\u0cc1 \u0caa\u0ccd\u0cb0\u0cb6\u0ccd\u0ca8\u0cbf\u0cb8\u0cbf\u0ca6\u0cb0\u0cc1. \u0cb5\u0cbf\u0cb0\u0ccb\u0ca7 \u0caa\u0c95\u0ccd\u0cb7\u0ca6\u0cb5\u0cb0\u0ca8\u0ccd\u0ca8\u0cc1 \u0cae\u0cc1\u0c97\u0cbf\u0cb8\u0cc1\u0cb5 \u0ca4\u0c82\u0ca4\u0ccd\u0cb0\u0cb5\u0ca8\u0ccd\u0ca8\u0cc1 \u0cb8\u0cb9\u0cbf\u0cb8\u0cb2\u0cc1 \u0cb8\u0cbe\u0ca7\u0ccd\u0caf\u0cb5\u0cbf\u0cb2\u0ccd\u0cb2. \u0c9c\u0ca8 \u0c87\u0ca6\u0cb0 \u0cb5\u0cbf\u0cb0\u0cc1\u0ca6\u0ccd\u0ca7 \u0c8e\u0ca6\u0ccd\u0ca6\u0cc1 \u0ca8\u0cbf\u0c82\u0ca4\u0cbf\u0ca6\u0ccd\u0ca6\u0cbe\u0cb0\u0cc6. \u0c87\u0ca6\u0ca8\u0ccd\u0ca8\u0cc1 \u0c95\u0cc7\u0c82\u0ca6\u0ccd\u0cb0\u0c95\u0ccd\u0c95\u0cc6 \u0ca4\u0ca1\u0cc6\u0caf\u0cb2\u0cc1 \u0cb8\u0cbe\u0ca7\u0ccd\u0caf\u0cb5\u0cbf\u0cb2\u0ccd\u0cb2 \u0c8e\u0c82\u0ca6\u0cb0\u0cc1.<\/p>","date":"2019-09-11 12:51:47","pin":"0","status":"0"},{"title":"asdsadsad","content":"<p>\u00a0asda sadsa<img src=\"http:\/\/cms.newindianexpress.com\/FCKeditor\/fckeditor_img\/image\/Congress_ANI.jpg\" width=\"1024\" height=\"576\" alt=\"\" \/><\/p>","date":"2019-09-11 12:57:02","pin":"0","status":"0"},{"title":"\u0cb8\u0cae\u0cbe\u0c9c\u0c95\u0ccd\u0c95\u0cc6 \u0c95\u0cb3\u0c82\u0c95 \u0ca4\u0cb0\u0cb2\u0cc1 \u0caf\u0ca4\u0ccd\u0ca8: \u0c92\u0c95\u0ccd\u0c95\u0cb2\u0cbf\u0c97 \u0ca8\u0cbe\u0caf\u0c95\u0cb0 \u0c86\u0c95\u0ccd\u0cb0\u0ccb\u0cb6","content":"<p>\u0c92\u0c95\u0ccd\u0c95\u0cb2\u0cbf\u0c97 \u0cb8\u0cae\u0cbe\u0c9c\u0c95\u0ccd\u0c95\u0cc6 \u0c95\u0cb3\u0c82\u0c95 \u0ca4\u0cb0\u0cc1\u0cb5 \u0caf\u0ca4\u0ccd\u0ca8 \u0ca8\u0ca1\u0cc6\u0caf\u0cc1\u0ca4\u0ccd\u0ca4\u0cbf\u0ca6\u0ccd\u0ca6\u0cc1, \u0c87\u0ca6\u0ca8\u0ccd\u0ca8\u0cc1 \u0c92\u0c97\u0ccd\u0c97\u0c9f\u0ccd\u0c9f\u0cbf\u0ca8\u0cbf\u0c82\u0ca6 \u0c8e\u0ca6\u0cc1\u0cb0\u0cbf\u0cb8\u0cac\u0cc7\u0c95\u0cc1 \u0c8e\u0c82\u0ca6\u0cc1 \u0c92\u0c95\u0ccd\u0c95\u0cb2\u0cbf\u0c97 \u0cb8\u0cae\u0cbe\u0c9c\u0ca6 \u0ca8\u0cbe\u0caf\u0c95\u0cb0\u0cc1 \u0cb9\u0cc7\u0cb3\u0cbf\u0ca6\u0cb0\u0cc1. \u0ca8\u0c97\u0cb0\u0ca6 \u0ca8\u0ccd\u0caf\u0cbe\u0cb7\u0ca8\u0cb2\u0ccd \u0c95\u0cbe\u0cb2\u0cc7\u0c9c\u0cc1 \u0cae\u0cc8\u0ca6\u0cbe\u0ca8\u0ca6\u0cb2\u0ccd\u0cb2\u0cbf \u0c86\u0cb0\u0c82\u0cad\u0cb5\u0cbe\u0c97\u0cbf\u0cb0\u0cc1\u0cb5 \u0caa\u0ccd\u0cb0\u0ca4\u0cbf\u0cad\u0c9f\u0ca8\u0cbe \u0caa\u0ccd\u0cb0\u0ca6\u0cb0\u0ccd\u0cb6\u0ca8\u0ca6\u0cb2\u0ccd\u0cb2\u0cbf \u0c92\u0c95\u0ccd\u0c95\u0cb2\u0cbf\u0c97 \u0cae\u0cc1\u0c96\u0c82\u0ca1 \u0cb0\u0cb5\u0cbf\u0cb6\u0c82\u0c95\u0cb0\u0ccd \u0c85\u0cb5\u0cb0\u0cc1 \u0c88 \u0cae\u0ca8\u0cb5\u0cbf \u0cae\u0cbe\u0ca1\u0cbf\u0ca6\u0cb0\u0cc1. \u0c87\u0ca8\u0ccd\u0ca8\u0cc2\u0cb0\u0c95\u0ccd\u0c95\u0cc2 \u0c85\u0ca7\u0cbf\u0c95 \u0c92\u0c95\u0ccd\u0c95\u0cb2\u0cbf\u0c97 \u0cb8\u0c82\u0c98\u0c9f\u0ca8\u0cc6\u0c97\u0cb3\u0cc1 \u0c92\u0c97\u0ccd\u0c97\u0c9f\u0ccd\u0c9f\u0cbf\u0ca8\u0cbf\u0c82\u0ca6 \u0cb6\u0cbf\u0cb5\u0c95\u0cc1\u0cae\u0cbe\u0cb0\u0ccd \u0c85\u0cb5\u0cb0 \u0cac\u0cc6\u0ca8\u0ccd\u0ca8\u0cbf\u0c97\u0cbf\u0cb5\u0cc6 \u0c8e\u0c82\u0ca6\u0cb0\u0cc1.<\/p>","date":"2019-09-11 12:57:25","pin":"0","status":"1"},{"title":"wqewqewqewq","content":"<p>\u00a0wqewqe<img src=\"http:\/\/cms.kannadaprabha.com\/FCKeditor\/fckeditor_img\/image\/Dr%20Boora%20Narsaiah%20Goud%20TRS(1).jpg\" width=\"1420\" height=\"953\" alt=\"\" \/><\/p>","date":"2019-09-11 12:59:03","pin":"0","status":"0"},{"title":"\u0ca1\u0cbf\u0c95\u0cc6\u0cb6\u0cbf \u0caa\u0cb0 \u0caa\u0ccd\u0cb0\u0ca4\u0cbf\u0cad\u0c9f\u0ca8\u0cc6: \u0ca8\u0c97\u0cb0\u0ca6\u0cb2\u0ccd\u0cb2\u0cbf \u0cad\u0cbe\u0cb0\u0cc0 \u0cad\u0ca6\u0ccd\u0cb0\u0ca4\u0cc6, 5 \u0cb8\u0cbe\u0cb5\u0cbf\u0cb0\u0c95\u0ccd\u0c95\u0cc2 \u0cb9\u0cc6\u0c9a\u0ccd\u0c9a\u0cc1 \u0caa\u0cca\u0cb2\u0cc0\u0cb8\u0cb0 \u0ca8\u0cbf\u0caf\u0ccb\u0c9c\u0ca8\u0cc6","content":"<blockquote class=\"twitter-tweet\"><p lang=\"und\" dir=\"ltr\">\u0ca1\u0cbf\u0c95\u0cc6\u0cb6\u0cbf \u0caa\u0cb0 \u0caa\u0ccd\u0cb0\u0ca4\u0cbf\u0cad\u0c9f\u0ca8\u0cc6: \u0ca8\u0c97\u0cb0\u0ca6\u0cb2\u0ccd\u0cb2\u0cbf \u0cad\u0cbe\u0cb0\u0cc0 \u0cad\u0ca6\u0ccd\u0cb0\u0ca4\u0cc6, 5 \u0cb8\u0cbe\u0cb5\u0cbf\u0cb0\u0c95\u0ccd\u0c95\u0cc2 \u0cb9\u0cc6\u0c9a\u0ccd\u0c9a\u0cc1 \u0caa\u0cca\u0cb2\u0cc0\u0cb8\u0cb0 \u0ca8\u0cbf\u0caf\u0ccb\u0c9c\u0ca8\u0cc6<br>Bengaluru: Top cop warns against violence during DKS rally<a href=\"https:\/\/twitter.com\/hashtag\/Bengaluru?src=hash&ref_src=twsrc%5Etfw\">#Bengaluru<\/a> <a href=\"https:\/\/twitter.com\/hashtag\/Protest?src=hash&ref_src=twsrc%5Etfw\">#Protest<\/a> <a href=\"https:\/\/twitter.com\/hashtag\/DKShivakumar?src=hash&ref_src=twsrc%5Etfw\">#DKShivakumar<\/a> <a href=\"https:\/\/twitter.com\/hashtag\/Politics?src=hash&ref_src=twsrc%5Etfw\">#Politics<\/a> <a href=\"https:\/\/twitter.com\/hashtag\/%E0%B2%AC%E0%B3%86%E0%B2%82%E0%B2%97%E0%B2%B3%E0%B3%82%E0%B2%B0%E0%B3%81?src=hash&ref_src=twsrc%5Etfw\">#\u0cac\u0cc6\u0c82\u0c97\u0cb3\u0cc2\u0cb0\u0cc1<\/a> <a href=\"https:\/\/twitter.com\/hashtag\/%E0%B2%AA%E0%B3%8D%E0%B2%B0%E0%B2%A4%E0%B2%BF%E0%B2%AD%E0%B2%9F%E0%B2%A8%E0%B3%86?src=hash&ref_src=twsrc%5Etfw\">#\u0caa\u0ccd\u0cb0\u0ca4\u0cbf\u0cad\u0c9f\u0ca8\u0cc6<\/a> <a href=\"https:\/\/twitter.com\/hashtag\/%E0%B2%A1%E0%B2%BF%E0%B2%95%E0%B3%86%E0%B2%B6%E0%B2%BF%E0%B2%B5%E0%B2%95%E0%B3%81%E0%B2%AE%E0%B2%BE%E0%B2%B0%E0%B3%8D?src=hash&ref_src=twsrc%5Etfw\">#\u0ca1\u0cbf\u0c95\u0cc6\u0cb6\u0cbf\u0cb5\u0c95\u0cc1\u0cae\u0cbe\u0cb0\u0ccd<\/a> <a href=\"https:\/\/twitter.com\/hashtag\/%E0%B2%B0%E0%B2%BE%E0%B2%9C%E0%B2%95%E0%B3%80%E0%B2%AF?src=hash&ref_src=twsrc%5Etfw\">#\u0cb0\u0cbe\u0c9c\u0c95\u0cc0\u0caf<\/a><br>Read more here: <a href=\"https:\/\/t.co\/7Ktov6IahD\">https:\/\/t.co\/7Ktov6IahD<\/a><\/p>\u2014 kannadaprabha (@KannadaPrabha) <a href=\"https:\/\/twitter.com\/KannadaPrabha\/status\/1171621407626842112?ref_src=twsrc%5Etfw\">September 11, 2019<\/a><\/blockquote> <script async src=\"https:\/\/platform.twitter.com\/widgets.js\" charset=\"utf-8\"><\/script>","date":"2019-09-11 12:59:47","pin":"0","status":"1"},{"title":"\u0cb0\u0cbe\u0c9c\u0c95\u0cc0\u0caf \u0ca6\u0ccd\u0cb5\u0cc7\u0cb7\u0c95\u0ccd\u0c95\u0cc6 \u0ca8\u0cbe\u0ca8\u0cc1 \u0c97\u0cc1\u0cb0\u0cbf\u0caf\u0cbe\u0c97\u0cbf\u0ca6\u0ccd\u0ca6\u0cc7\u0ca8\u0cc6: \u0ca1\u0cbf.\u0c95\u0cc6.\u0cb6\u0cbf\u0cb5\u0c95\u0cc1\u0cae\u0cbe\u0cb0\u0ccd","content":"<blockquote class=\"twitter-tweet\"><p lang=\"und\" dir=\"ltr\">\u0cb0\u0cbe\u0c9c\u0c95\u0cc0\u0caf \u0ca6\u0ccd\u0cb5\u0cc7\u0cb7\u0c95\u0ccd\u0c95\u0cc6 \u0ca8\u0cbe\u0ca8\u0cc1 \u0c97\u0cc1\u0cb0\u0cbf\u0caf\u0cbe\u0c97\u0cbf\u0ca6\u0ccd\u0ca6\u0cc7\u0ca8\u0cc6: \u0ca1\u0cbf.\u0c95\u0cc6.\u0cb6\u0cbf\u0cb5\u0c95\u0cc1\u0cae\u0cbe\u0cb0\u0ccd<br>I am target of vendetta politics says DK Shivakumar<a href=\"https:\/\/twitter.com\/hashtag\/Bengaluru?src=hash&ref_src=twsrc%5Etfw\">#Bengaluru<\/a> <a href=\"https:\/\/twitter.com\/hashtag\/Protest?src=hash&ref_src=twsrc%5Etfw\">#Protest<\/a> <a href=\"https:\/\/twitter.com\/hashtag\/DKShivakumar?src=hash&ref_src=twsrc%5Etfw\">#DKShivakumar<\/a> <a href=\"https:\/\/twitter.com\/hashtag\/Politics?src=hash&ref_src=twsrc%5Etfw\">#Politics<\/a> <a href=\"https:\/\/twitter.com\/hashtag\/%E0%B2%AC%E0%B3%86%E0%B2%82%E0%B2%97%E0%B2%B3%E0%B3%82%E0%B2%B0%E0%B3%81?src=hash&ref_src=twsrc%5Etfw\">#\u0cac\u0cc6\u0c82\u0c97\u0cb3\u0cc2\u0cb0\u0cc1<\/a> <a href=\"https:\/\/twitter.com\/hashtag\/%E0%B2%AA%E0%B3%8D%E0%B2%B0%E0%B2%A4%E0%B2%BF%E0%B2%AD%E0%B2%9F%E0%B2%A8%E0%B3%86?src=hash&ref_src=twsrc%5Etfw\">#\u0caa\u0ccd\u0cb0\u0ca4\u0cbf\u0cad\u0c9f\u0ca8\u0cc6<\/a> <a href=\"https:\/\/twitter.com\/hashtag\/%E0%B2%A1%E0%B2%BF%E0%B2%95%E0%B3%86%E0%B2%B6%E0%B2%BF%E0%B2%B5%E0%B2%95%E0%B3%81%E0%B2%AE%E0%B2%BE%E0%B2%B0%E0%B3%8D?src=hash&ref_src=twsrc%5Etfw\">#\u0ca1\u0cbf\u0c95\u0cc6\u0cb6\u0cbf\u0cb5\u0c95\u0cc1\u0cae\u0cbe\u0cb0\u0ccd<\/a> <a href=\"https:\/\/twitter.com\/hashtag\/%E0%B2%B0%E0%B2%BE%E0%B2%9C%E0%B2%95%E0%B3%80%E0%B2%AF?src=hash&ref_src=twsrc%5Etfw\">#\u0cb0\u0cbe\u0c9c\u0c95\u0cc0\u0caf<\/a><br>Read more here: <a href=\"https:\/\/t.co\/swQTShNPMg\">https:\/\/t.co\/swQTShNPMg<\/a><\/p>\u2014 kannadaprabha (@KannadaPrabha) <a href=\"https:\/\/twitter.com\/KannadaPrabha\/status\/1171618227308285953?ref_src=twsrc%5Etfw\">September 11, 2019<\/a><\/blockquote> <script async src=\"https:\/\/platform.twitter.com\/widgets.js\" charset=\"utf-8\"><\/script>","date":"2019-09-11 01:00:16","pin":"0","status":"0"},{"title":"\u0ca1\u0cbf\u0c95\u0cc6 \u0cb6\u0cbf\u0cb5\u0c95\u0cc1\u0cae\u0cbe\u0cb0\u0ccd \u0cac\u0c82\u0ca7\u0ca8 \u0cb5\u0cbf\u0cb0\u0ccb\u0ca7\u0cbf\u0cb8\u0cbf \u0c92\u0c95\u0ccd\u0c95\u0cb2\u0cbf\u0c97\u0cb0 \u0cac\u0cc3\u0cb9\u0ca4\u0ccd \u0caa\u0ccd\u0cb0\u0ca4\u0cbf\u0cad\u0c9f\u0ca8\u0cc6: \u0cac\u0cbf\u0c97\u0cbf \u0caa\u0cca\u0cb2\u0cc0\u0cb8\u0ccd \u0cac\u0c82\u0ca6\u0ccb\u0cac\u0cb8\u0ccd\u0ca4\u0ccd","content":"<blockquote class=\"twitter-tweet\"><p lang=\"kn\" dir=\"ltr\">\u0ca1\u0cbf\u0c95\u0cc6 \u0cb6\u0cbf\u0cb5\u0c95\u0cc1\u0cae\u0cbe\u0cb0\u0ccd \u0cac\u0c82\u0ca7\u0ca8 \u0cb5\u0cbf\u0cb0\u0ccb\u0ca7\u0cbf\u0cb8\u0cbf \u0c92\u0c95\u0ccd\u0c95\u0cb2\u0cbf\u0c97\u0cb0 \u0cac\u0cc3\u0cb9\u0ca4\u0ccd \u0caa\u0ccd\u0cb0\u0ca4\u0cbf\u0cad\u0c9f\u0ca8\u0cc6: \u0cac\u0cbf\u0c97\u0cbf \u0caa\u0cca\u0cb2\u0cc0\u0cb8\u0ccd \u0cac\u0c82\u0ca6\u0ccb\u0cac\u0cb8\u0ccd\u0ca4\u0ccd <a href=\"https:\/\/twitter.com\/hashtag\/dkshivakumar?src=hash&ref_src=twsrc%5Etfw\">#dkshivakumar<\/a> <a href=\"https:\/\/twitter.com\/hashtag\/ED?src=hash&ref_src=twsrc%5Etfw\">#ED<\/a> <a href=\"https:\/\/twitter.com\/hashtag\/Arrested?src=hash&ref_src=twsrc%5Etfw\">#Arrested<\/a> <a href=\"https:\/\/twitter.com\/hashtag\/Protest?src=hash&ref_src=twsrc%5Etfw\">#Protest<\/a> <a href=\"https:\/\/twitter.com\/hashtag\/Bengaluru?src=hash&ref_src=twsrc%5Etfw\">#Bengaluru<\/a><a href=\"https:\/\/t.co\/eSUap8OYLd\">https:\/\/t.co\/eSUap8OYLd<\/a><\/p>\u2014 kannadaprabha (@KannadaPrabha) <a href=\"https:\/\/twitter.com\/KannadaPrabha\/status\/1171610531330953216?ref_src=twsrc%5Etfw\">September 11, 2019<\/a><\/blockquote> <script async src=\"https:\/\/platform.twitter.com\/widgets.js\" charset=\"utf-8\"><\/script>","date":"2019-09-11 01:02:42","pin":"0","status":"1"},{"title":"","content":"<p>\u00a0<img src=\"http:\/\/cms.kannadaprabha.com\/FCKeditor\/fckeditor_img\/image\/Chief%20Ministers-Delhi-EPS.jpg\" width=\"1280\" height=\"642\" alt=\"\" \/><\/p>","date":"2019-09-11 01:06:16","pin":"0","status":"0"},{"title":"\u0c95\u0cc7\u0c82\u0ca6\u0ccd\u0cb0 \u0cb8\u0cb0\u0ccd\u0c95\u0cbe\u0cb0\u0ca6 \u0cb8\u0cc7\u0ca1\u0cbf\u0ca8 \u0cb0\u0cbe\u0c9c\u0c95\u0cbe\u0cb0\u0ca3 \u0cb8\u0cb9\u0cbf\u0cb8\u0cb2\u0cb8\u0cbe\u0ca7\u0ccd\u0caf: \u0c95\u0cc6\u0caa\u0cbf\u0cb8\u0cbf\u0cb8\u0cbf \u0c85\u0ca7\u0ccd\u0caf\u0c95\u0ccd\u0cb7 \u0ca6\u0cbf\u0ca8\u0cc7\u0cb6\u0ccd \u0c97\u0cc1\u0c82\u0ca1\u0cc2\u0cb0\u0cbe\u0cb5\u0ccd","content":"<p>\u0c95\u0cbe\u0c82\u0c97\u0ccd\u0cb0\u0cc6\u0cb8\u0ccd \u0cb8\u0c9a\u0cbf\u0cb5 \u0ca1\u0cbf\u0c95\u0cc6 \u0cb6\u0cbf\u0cb5\u0c95\u0cc1\u0cae\u0cbe\u0cb0\u0ccd \u0cb0\u0ca8\u0ccd\u0ca8\u0cc1 \u0cac\u0c82\u0ca7\u0cbf\u0cb8\u0cc1\u0cb5 \u0cae\u0cc2\u0cb2\u0c95 \u0c95\u0cc7\u0c82\u0ca6\u0ccd\u0cb0 \u0cb8\u0cb0\u0ccd\u0c95\u0cbe\u0cb0 \u0cb8\u0cc7\u0ca1\u0cbf\u0ca8 \u0cb0\u0cbe\u0c9c\u0c95\u0cbe\u0cb0\u0ca3 \u0cae\u0cbe\u0ca1\u0cc1\u0ca4\u0ccd\u0ca4\u0cbf\u0ca6\u0ccd\u0ca6\u0cc1, \u0c95\u0cc7\u0c82\u0ca6\u0ccd\u0cb0\u0ca6 \u0cae\u0ccb\u0ca6\u0cbf \u0cb8\u0cb0\u0ccd\u0c95\u0cbe\u0cb0\u0ca6 \u0c88 \u0c95\u0ccd\u0cb0\u0cae\u0cb5\u0ca8\u0ccd\u0ca8\u0cc1 \u0cb0\u0cbe\u0c9c\u0ccd\u0caf\u0ca6 \u0c9c\u0ca8\u0cb0\u0cc1 \u0cb8\u0cb9\u0cbf\u0cb8\u0cc1\u0cb5\u0cc1\u0ca6\u0cbf\u0cb2\u0ccd\u0cb2. \u0c87\u0cb2\u0ccd\u0cb2\u0cbf \u0c87\u0c82\u0ca6\u0cc1 50 \u0cb8\u0cbe\u0cb5\u0cbf\u0cb0\u0ca6\u0cb7\u0ccd\u0ca1\u0cc1 \u0c9c\u0ca8 \u0cb8\u0cc7\u0cb0\u0cb2\u0cbf\u0ca6\u0ccd\u0ca6\u0cc1, \u0c87\u0ca6\u0cc1 \u0c95\u0cc7\u0c82\u0ca6\u0ccd\u0cb0\u0c95\u0ccd\u0c95\u0cc6 \u0ca8\u0cc0\u0ca1\u0cc1\u0cb5 \u0caa\u0ccd\u0cb0\u0ca4\u0ccd\u0caf\u0cc1\u0ca4\u0ccd\u0ca4\u0cb0 \u0c8e\u0c82\u0ca6\u0cb0\u0cc1. \u0c85\u0c82\u0ca4\u0cc6\u0caf\u0cc7 \u0c95\u0cc7\u0c82\u0ca6\u0ccd\u0cb0 \u0cb8\u0cb0\u0ccd\u0c95\u0cbe\u0cb0 \u0c90\u0c9f\u0cbf. \u0c87\u0ca1\u0cbf \u0c87\u0cb2\u0cbe\u0c96\u0cc6 \u0c97\u0cb3\u0ca8\u0ccd\u0ca8\u0cc1 \u0ca6\u0cc1\u0cb0\u0ccd\u0cac\u0cb3\u0c95\u0cc6 \u0cae\u0cbe\u0ca1\u0cc1\u0cb5\u0cc1\u0ca6\u0cc1 \u0caa\u0ccd\u0cb0\u0c9c\u0cbe\u0caa\u0ccd\u0cb0\u0cad\u0cc1\u0ca4\u0ccd\u0cb5\u0c95\u0ccd\u0c95\u0cc6 \u0c85\u0caa\u0cbe\u0caf\u0c95\u0cbe\u0cb0\u0cbf. \u0ca1\u0cbf\u0c95\u0cc6\u0cb6\u0cbf \u0c85\u0cb5\u0cb0\u0cc1 \u0ca4\u0ca8\u0cbf\u0c96\u0cc6\u0c97\u0cc6 \u0cb8\u0cb9\u0c95\u0cbe\u0cb0 \u0ca8\u0cc0\u0ca1\u0cbf\u0ca6 \u0cae\u0cc7\u0cb2\u0cc2 \u0c85\u0cb5\u0cb0\u0cbf\u0c97\u0cc6 \u0c95\u0cbf\u0cb0\u0cc1\u0c95\u0cc1\u0cb3 \u0ca8\u0cc0\u0ca1\u0cc1\u0cb5 \u0cb8\u0cb2\u0cc1\u0cb5\u0cbe\u0c97\u0cbf\u0caf\u0cc7 \u0c85\u0cb5\u0cb0\u0ca8\u0ccd\u0ca8\u0cc1 \u0cac\u0c82\u0ca7\u0cbf\u0cb8\u0cb2\u0cbe\u0c97\u0cbf\u0ca6\u0cc6. 3 \u0ca4\u0cbf\u0c82\u0c97\u0cb3\u0cb2\u0ccd\u0cb2\u0cbf \u0cac\u0ccd\u0caf\u0cbe\u0c82\u0c95\u0cc1\u0c97\u0cb3\u0cbf\u0c82\u0ca6 32 \u0cb8\u0cbe\u0cb5\u0cbf\u0cb0 \u0c95\u0ccb\u0c9f\u0cbf \u0cb2\u0cc2\u0c9f\u0cbf\u0caf\u0cbe\u0c97\u0cbf\u0ca6\u0cc6. \u0c85\u0ca6\u0ca8\u0ccd\u0ca8\u0cc1 \u0ca4\u0ca1\u0cc6\u0caf\u0cb2\u0cc1 \u0c8f\u0ca8\u0cc1 \u0c95\u0ccd\u0cb0\u0cae \u0c95\u0cc8\u0c97\u0cca\u0c82\u0ca1\u0cbf\u0ca6\u0ccd\u0ca6\u0cc0\u0cb0\u0cbf \u0c8e\u0c82\u0ca6\u0cc1 \u0c85\u0cb5\u0cb0\u0cc1 \u0caa\u0ccd\u0cb0\u0cb6\u0ccd\u0ca8\u0cbf\u0cb8\u0cbf\u0ca6\u0cb0\u0cc1. \u0cb5\u0cbf\u0cb0\u0ccb\u0ca7 \u0caa\u0c95\u0ccd\u0cb7\u0ca6\u0cb5\u0cb0\u0ca8\u0ccd\u0ca8\u0cc1 \u0cae\u0cc1\u0c97\u0cbf\u0cb8\u0cc1\u0cb5 \u0ca4\u0c82\u0ca4\u0ccd\u0cb0\u0cb5\u0ca8\u0ccd\u0ca8\u0cc1 \u0cb8\u0cb9\u0cbf\u0cb8\u0cb2\u0cc1 \u0cb8\u0cbe\u0ca7\u0ccd\u0caf\u0cb5\u0cbf\u0cb2\u0ccd\u0cb2. \u0c9c\u0ca8 \u0c87\u0ca6\u0cb0 \u0cb5\u0cbf\u0cb0\u0cc1\u0ca6\u0ccd\u0ca7 \u0c8e\u0ca6\u0ccd\u0ca6\u0cc1 \u0ca8\u0cbf\u0c82\u0ca4\u0cbf\u0ca6\u0ccd\u0ca6\u0cbe\u0cb0\u0cc6 \u0c8e\u0c82\u0ca6\u0cc1 \u0cb9\u0cc7\u0cb3\u0cbf\u0ca6\u0cb0\u0cc1.<img src=\"http:\/\/cms.kannadaprabha.com\/FCKeditor\/fckeditor_img\/image\/DKS01.jpg\" alt=\"Protest adainst DKS Arrest\" width=\"794\" height=\"450\" \/><\/p>","date":"2019-09-11 01:18:48","pin":"0","status":"0"},{"title":"\u0c90\u0c9f\u0cbf, \u0cb8\u0cbf\u0cac\u0cbf\u0c90 \u0c87\u0ca1\u0cbf\u0caf\u0cb2\u0ccd\u0cb2\u0cc2 \u0cac\u0cbf\u0c9c\u0cc6\u0caa\u0cbf \u0cb8\u0cc0\u0cb3\u0cc1 \u0ca8\u0cbe\u0caf\u0cbf\u0c97\u0cb3\u0cbf\u0ca6\u0ccd\u0ca6\u0cbe\u0cb0\u0cc6: \u0c95\u0cc3\u0cb7\u0ccd\u0ca3\u0cac\u0cc7\u0cb0\u0cc7\u0c97\u0ccc\u0ca1","content":"<blockquote class=\"twitter-tweet\"><p lang=\"kn\" dir=\"ltr\">\u0c90\u0c9f\u0cbf, \u0cb8\u0cbf\u0cac\u0cbf\u0c90 \u0c87\u0ca1\u0cbf\u0caf\u0cb2\u0ccd\u0cb2\u0cc2 \u0cac\u0cbf\u0c9c\u0cc6\u0caa\u0cbf \u0cb8\u0cc0\u0cb3\u0cc1 \u0ca8\u0cbe\u0caf\u0cbf\u0c97\u0cb3\u0cbf\u0ca6\u0ccd\u0ca6\u0cbe\u0cb0\u0cc6: \u0c95\u0cc3\u0cb7\u0ccd\u0ca3\u0cac\u0cc7\u0cb0\u0cc7\u0c97\u0ccc\u0ca1 <a href=\"https:\/\/twitter.com\/hashtag\/Bengaluru?src=hash&ref_src=twsrc%5Etfw\">#Bengaluru<\/a> <a href=\"https:\/\/twitter.com\/hashtag\/ProtestagainstDKSarrest?src=hash&ref_src=twsrc%5Etfw\">#ProtestagainstDKSarrest<\/a> <a href=\"https:\/\/twitter.com\/hashtag\/Congress?src=hash&ref_src=twsrc%5Etfw\">#Congress<\/a> <a href=\"https:\/\/twitter.com\/hashtag\/ED?src=hash&ref_src=twsrc%5Etfw\">#ED<\/a> <a href=\"https:\/\/twitter.com\/hashtag\/DKShivakumar?src=hash&ref_src=twsrc%5Etfw\">#DKShivakumar<\/a> <a href=\"https:\/\/twitter.com\/hashtag\/KrishnaByreGowda?src=hash&ref_src=twsrc%5Etfw\">#KrishnaByreGowda<\/a> <a href=\"https:\/\/twitter.com\/hashtag\/%E0%B2%AC%E0%B3%86%E0%B2%82%E0%B2%97%E0%B2%B3%E0%B3%82%E0%B2%B0%E0%B3%81?src=hash&ref_src=twsrc%5Etfw\">#\u0cac\u0cc6\u0c82\u0c97\u0cb3\u0cc2\u0cb0\u0cc1<\/a> <a href=\"https:\/\/twitter.com\/hashtag\/%E0%B2%A1%E0%B2%BF%E0%B2%95%E0%B3%86%E0%B2%B6%E0%B2%BF%E0%B2%AC%E0%B2%82%E0%B2%A7%E0%B2%A8%E0%B2%B5%E0%B2%BF%E0%B2%B0%E0%B3%8B%E0%B2%A7%E0%B2%BF%E0%B2%B8%E0%B2%BF%E0%B2%AA%E0%B3%8D%E0%B2%B0%E0%B2%A4%E0%B2%BF%E0%B2%AD%E0%B2%9F%E0%B2%A8%E0%B3%86?src=hash&ref_src=twsrc%5Etfw\">#\u0ca1\u0cbf\u0c95\u0cc6\u0cb6\u0cbf\u0cac\u0c82\u0ca7\u0ca8\u0cb5\u0cbf\u0cb0\u0ccb\u0ca7\u0cbf\u0cb8\u0cbf\u0caa\u0ccd\u0cb0\u0ca4\u0cbf\u0cad\u0c9f\u0ca8\u0cc6<\/a> <a href=\"https:\/\/twitter.com\/hashtag\/%E0%B2%95%E0%B2%BE%E0%B2%82%E0%B2%97%E0%B3%8D%E0%B2%B0%E0%B3%86%E0%B2%B8%E0%B3%8D?src=hash&ref_src=twsrc%5Etfw\">#\u0c95\u0cbe\u0c82\u0c97\u0ccd\u0cb0\u0cc6\u0cb8\u0ccd<\/a> <a href=\"https:\/\/twitter.com\/hashtag\/%E0%B2%87%E0%B2%A1%E0%B2%BF?src=hash&ref_src=twsrc%5Etfw\">#\u0c87\u0ca1\u0cbf<\/a> <a href=\"https:\/\/twitter.com\/hashtag\/%E0%B2%A1%E0%B2%BF%E0%B2%95%E0%B3%86%E0%B2%B6%E0%B2%BF%E0%B2%B5%E0%B2%95%E0%B3%81%E0%B2%AE%E0%B2%BE%E0%B2%B0%E0%B3%8D?src=hash&ref_src=twsrc%5Etfw\">#\u0ca1\u0cbf\u0c95\u0cc6\u0cb6\u0cbf\u0cb5\u0c95\u0cc1\u0cae\u0cbe\u0cb0\u0ccd<\/a> <a href=\"https:\/\/twitter.com\/hashtag\/%E0%B2%95%E0%B3%83%E0%B2%B7%E0%B3%8D%E0%B2%A3%E0%B2%AC%E0%B3%88%E0%B2%B0%E0%B3%87%E0%B2%97%E0%B3%8C%E0%B2%A1?src=hash&ref_src=twsrc%5Etfw\">#\u0c95\u0cc3\u0cb7\u0ccd\u0ca3\u0cac\u0cc8\u0cb0\u0cc7\u0c97\u0ccc\u0ca1<\/a><br>Read more here: <a href=\"https:\/\/t.co\/ScwtDK6Ki1\">https:\/\/t.co\/ScwtDK6Ki1<\/a><\/p>\u2014 kannadaprabha (@KannadaPrabha) <a href=\"https:\/\/twitter.com\/KannadaPrabha\/status\/1171696890502467584?ref_src=twsrc%5Etfw\">September 11, 2019<\/a><\/blockquote> <script async src=\"https:\/\/platform.twitter.com\/widgets.js\" charset=\"utf-8\"><\/script>","date":"2019-09-11 01:40:16","pin":"0","status":"1"},{"title":"\u0c95\u0cc7\u0c82\u0ca6\u0ccd\u0cb0 \u0cb8\u0cb0\u0ccd\u0c95\u0cbe\u0cb0\u0ca6 \u0cb8\u0cc7\u0ca1\u0cbf\u0ca8 \u0cb0\u0cbe\u0c9c\u0c95\u0cbe\u0cb0\u0ca3 \u0cb8\u0cb9\u0cbf\u0cb8\u0cb2\u0cb8\u0cbe\u0ca7\u0ccd\u0caf: \u0c95\u0cc6\u0caa\u0cbf\u0cb8\u0cbf\u0cb8\u0cbf \u0c85\u0ca7\u0ccd\u0caf\u0c95\u0ccd\u0cb7 \u0ca6\u0cbf\u0ca8\u0cc7\u0cb6\u0ccd \u0c97\u0cc1\u0c82\u0ca1\u0cc2\u0cb0\u0cbe\u0cb5\u0ccd","content":"<blockquote class=\"twitter-tweet\"><p lang=\"kn\" dir=\"ltr\">\u0c95\u0cc7\u0c82\u0ca6\u0ccd\u0cb0 \u0cb8\u0cb0\u0ccd\u0c95\u0cbe\u0cb0\u0ca6 \u0cb8\u0cc7\u0ca1\u0cbf\u0ca8 \u0cb0\u0cbe\u0c9c\u0c95\u0cbe\u0cb0\u0ca3 \u0cb8\u0cb9\u0cbf\u0cb8\u0cb2\u0cb8\u0cbe\u0ca7\u0ccd\u0caf: \u0c95\u0cc6\u0caa\u0cbf\u0cb8\u0cbf\u0cb8\u0cbf \u0c85\u0ca7\u0ccd\u0caf\u0c95\u0ccd\u0cb7 \u0ca6\u0cbf\u0ca8\u0cc7\u0cb6\u0ccd \u0c97\u0cc1\u0c82\u0ca1\u0cc2\u0cb0\u0cbe\u0cb5\u0ccd <a href=\"https:\/\/twitter.com\/hashtag\/ProtestagainstDKSarrest?src=hash&ref_src=twsrc%5Etfw\">#ProtestagainstDKSarrest<\/a> <a href=\"https:\/\/twitter.com\/hashtag\/Congress?src=hash&ref_src=twsrc%5Etfw\">#Congress<\/a> <a href=\"https:\/\/twitter.com\/hashtag\/ED?src=hash&ref_src=twsrc%5Etfw\">#ED<\/a> <a href=\"https:\/\/twitter.com\/hashtag\/DKShivakumar?src=hash&ref_src=twsrc%5Etfw\">#DKShivakumar<\/a> <a href=\"https:\/\/twitter.com\/hashtag\/DineshGundurao?src=hash&ref_src=twsrc%5Etfw\">#DineshGundurao<\/a> <a href=\"https:\/\/twitter.com\/hashtag\/%E0%B2%A1%E0%B2%BF%E0%B2%95%E0%B3%86%E0%B2%B6%E0%B2%BF%E0%B2%AC%E0%B2%82%E0%B2%A7%E0%B2%A8%E0%B2%B5%E0%B2%BF%E0%B2%B0%E0%B3%8B%E0%B2%A7%E0%B2%BF%E0%B2%B8%E0%B2%BF%E0%B2%AA%E0%B3%8D%E0%B2%B0%E0%B2%A4%E0%B2%BF%E0%B2%AD%E0%B2%9F%E0%B2%A8%E0%B3%86?src=hash&ref_src=twsrc%5Etfw\">#\u0ca1\u0cbf\u0c95\u0cc6\u0cb6\u0cbf\u0cac\u0c82\u0ca7\u0ca8\u0cb5\u0cbf\u0cb0\u0ccb\u0ca7\u0cbf\u0cb8\u0cbf\u0caa\u0ccd\u0cb0\u0ca4\u0cbf\u0cad\u0c9f\u0ca8\u0cc6<\/a> <a href=\"https:\/\/twitter.com\/hashtag\/%E0%B2%95%E0%B2%BE%E0%B2%82%E0%B2%97%E0%B3%8D%E0%B2%B0%E0%B3%86%E0%B2%B8%E0%B3%8D?src=hash&ref_src=twsrc%5Etfw\">#\u0c95\u0cbe\u0c82\u0c97\u0ccd\u0cb0\u0cc6\u0cb8\u0ccd<\/a> <a href=\"https:\/\/twitter.com\/hashtag\/%E0%B2%87%E0%B2%A1%E0%B2%BF?src=hash&ref_src=twsrc%5Etfw\">#\u0c87\u0ca1\u0cbf<\/a> <a href=\"https:\/\/twitter.com\/hashtag\/%E0%B2%A1%E0%B2%BF%E0%B2%95%E0%B3%86%E0%B2%B6%E0%B2%BF%E0%B2%B5%E0%B2%95%E0%B3%81%E0%B2%AE%E0%B2%BE%E0%B2%B0%E0%B3%8D?src=hash&ref_src=twsrc%5Etfw\">#\u0ca1\u0cbf\u0c95\u0cc6\u0cb6\u0cbf\u0cb5\u0c95\u0cc1\u0cae\u0cbe\u0cb0\u0ccd<\/a> <a href=\"https:\/\/twitter.com\/hashtag\/%E0%B2%A6%E0%B2%BF%E0%B2%A8%E0%B3%87%E0%B2%B6%E0%B3%8D%E0%B2%97%E0%B3%81%E0%B2%82%E0%B2%A1%E0%B3%82%E0%B2%B0%E0%B2%BE%E0%B2%B5%E0%B3%8D?src=hash&ref_src=twsrc%5Etfw\">#\u0ca6\u0cbf\u0ca8\u0cc7\u0cb6\u0ccd\u0c97\u0cc1\u0c82\u0ca1\u0cc2\u0cb0\u0cbe\u0cb5\u0ccd<\/a><br>Read more here: <a href=\"https:\/\/t.co\/IlFwlxjBKi\">https:\/\/t.co\/IlFwlxjBKi<\/a><\/p>\u2014 kannadaprabha (@KannadaPrabha) <a href=\"https:\/\/twitter.com\/KannadaPrabha\/status\/1171700360789909504?ref_src=twsrc%5Etfw\">September 11, 2019<\/a><\/blockquote> <script async src=\"https:\/\/platform.twitter.com\/widgets.js\" charset=\"utf-8\"><\/script>","date":"2019-09-11 01:52:35","pin":"0","status":"1"},{"title":"","content":"<p>\u0ca1\u0cbf\u0c95\u0cc6 \u0cb6\u0cbf\u0cb5\u0c95\u0cc1\u0cae\u0cbe\u0cb0\u0ccd \u0c95\u0cbe\u0ca8\u0cc2\u0ca8\u0cc1 \u0cac\u0cbe\u0cb9\u0cbf\u0cb0\u0cb5\u0cbe\u0c97\u0cbf \u0caf\u0cbe\u0cb5\u0cc1\u0ca6\u0cc7 \u0ca4\u0cb0\u0cb9\u0ca6 \u0cb9\u0ca3 \u0cb8\u0c82\u0caa\u0cbe\u0ca6\u0cbf\u0cb8\u0cbf\u0cb2\u0ccd\u0cb2: \u0cae\u0cbe\u0c9c\u0cbf \u0cb8\u0c9a\u0cbf\u0cb5 \u0c9a\u0cc6\u0cb2\u0cc1\u0cb5\u0cb0\u0cbe\u0caf\u0cb8\u0ccd\u0cb5\u0cbe\u0cae\u0cbf<\/p>","date":"2019-09-11 01:54:51","pin":"0","status":"1"},{"title":"","content":"<p>\u00a0\u0cab\u0ccd\u0cb0\u0cc0\u0ca1\u0c82 \u0caa\u0cbe\u0cb0\u0ccd\u0c95\u0ccd \u0ca4\u0cb2\u0cc1\u0caa\u0cbf\u0ca6 \u0cac\u0cc3\u0cb9\u0ca4\u0ccd \u0caa\u0ccd\u0cb0\u0ca4\u0cbf\u0cad\u0c9f\u0ca8\u0cbe \u0cb0\u0ccd\u0caf\u0cbe\u0cb2\u0cbf, \u0ca8\u0cbe\u0caf\u0c95\u0cb0\u0cbf\u0c82\u0ca6 \u0c95\u0cc7\u0c82\u0ca6\u0ccd\u0cb0 \u0cb8\u0cb0\u0ccd\u0c95\u0cbe\u0cb0\u0ca6 \u0cb5\u0cbf\u0cb0\u0cc1\u0ca6\u0ccd\u0ca6 \u0cb5\u0cbe\u0c97\u0ccd\u0ca6\u0cbe\u0cb3\u0cbf<\/p>","date":"2019-09-11 02:06:40","pin":"0","status":"1"},{"title":"\u0c92\u0c95\u0ccd\u0c95\u0cb2\u0cbf\u0c97 \u0cb8\u0c82\u0c98\u0ca6 \u0c95\u0cbe\u0cb0\u0ccd\u0caf\u0c95\u0cb0\u0ccd\u0ca4\u0cb0\u0cbf\u0c82\u0ca6 '\u0cb0\u0cbe\u0c9c\u0cad\u0cb5\u0ca8 \u0c9a\u0cb2\u0ccb' ","content":"<blockquote class=\"twitter-tweet\"><p lang=\"en\" dir=\"ltr\">Bengaluru: Members of the Vokkaliga Sangha heading towards Raj Bhavan in protest against arrest of Congress leader DK Shivakumar by Enforcement Directorate (ED). Shivakumar belongs to the Vokkaliga community. <a href=\"https:\/\/twitter.com\/hashtag\/Karnataka?src=hash&ref_src=twsrc%5Etfw\">#Karnataka<\/a> <a href=\"https:\/\/t.co\/ikWnWnmsCm\">https:\/\/t.co\/ikWnWnmsCm<\/a> <a href=\"https:\/\/t.co\/La9TRW7ODf\">pic.twitter.com\/La9TRW7ODf<\/a><\/p>\u2014 ANI (@ANI) <a href=\"https:\/\/twitter.com\/ANI\/status\/1171700696330039296?ref_src=twsrc%5Etfw\">September 11, 2019<\/a><\/blockquote> <script async src=\"https:\/\/platform.twitter.com\/widgets.js\" charset=\"utf-8\"><\/script> ","date":"2019-09-11 02:22:33","pin":"0","status":"1"},{"title":"","content":"<p>\u00a0<a href=\"https:\/\/www.udayavani.com\/homepage-karnataka-edition\/breakingnews-karnataka-edition\/congress-leaders-protest-bengaluru\" class=\"p-owl-news ticker_item\" style=\"box-sizing: border-box; margin: 0px 40px 0px 0px; padding: 6px 0px 0px; font-variant-numeric: normal; font-variant-east-asian: normal; font-stretch: normal; font-size: 15px; line-height: normal; font-family: NotoSansKannada-Bold, Arial, Helvetica, sans-serif; vertical-align: baseline; background: 0px 0px rgb(255, 228, 131); text-decoration-line: none; outline: 0px; color: rgb(0, 0, 0); cursor: pointer; transition: all 0.3s ease 0s; display: inline-block; white-space: nowrap;\">\u0cac\u0cbf\u0c9c\u0cc6\u0caa\u0cbf \u0ca6\u0ccd\u0cb5\u0cc7\u0cb7\u0ca6 \u0cb0\u0cbe\u0c9c\u0c95\u0cbe\u0cb0\u0ca3 \u0cae\u0cbe\u0ca1\u0cc1\u0ca4\u0ccd\u0ca4\u0cbf\u0ca6\u0cc6: \u0ca1\u0cbf\u0c95\u0cc6\u0cb6\u0cbf \u0cac\u0c82\u0ca7\u0ca8\u0c95\u0ccd\u0c95\u0cc6 \u0c95\u0cbe\u0c82\u0c97\u0ccd\u0cb0\u0cc6\u0cb8\u0ccd \u0ca8\u0cbe\u0caf\u0c95\u0cb0 \u0c86\u0c95\u0ccd\u0cb0\u0ccb\u0cb6<\/a><\/p>","date":"2019-09-11 02:32:50","pin":"0","status":"0"},{"title":"","content":"<p>\u00a0\u0cac\u0cbf\u0c9c\u0cc6\u0caa\u0cbf \u0ca6\u0ccd\u0cb5\u0cc7\u0cb7\u0ca6 \u0cb0\u0cbe\u0c9c\u0c95\u0cbe\u0cb0\u0ca3 \u0cae\u0cbe\u0ca1\u0cc1\u0ca4\u0ccd\u0ca4\u0cbf\u0ca6\u0cc6: \u0ca1\u0cbf\u0c95\u0cc6\u0cb6\u0cbf \u0cac\u0c82\u0ca7\u0ca8\u0c95\u0ccd\u0c95\u0cc6 \u0c95\u0cbe\u0c82\u0c97\u0ccd\u0cb0\u0cc6\u0cb8\u0ccd \u0ca8\u0cbe\u0caf\u0c95\u0cb0 \u0c86\u0c95\u0ccd\u0cb0\u0ccb\u0cb6<\/p>\n<div>\u00a0<\/div>","date":"2019-09-11 02:34:27","pin":"0","status":"1"},{"title":"\u0ca1\u0cbf\u0c95\u0cc6\u0cb6\u0cbf \u0cac\u0c82\u0ca7\u0ca8 \u0cb5\u0cbf\u0cb0\u0ccb\u0ca7\u0cbf\u0cb8\u0cbf \u0c92\u0c95\u0ccd\u0c95\u0cb2\u0cbf\u0c97 \u0cb8\u0cae\u0cc1\u0ca6\u0cbe\u0caf\u0ca6 \u0caa\u0ccd\u0cb0\u0ca4\u0cbf\u0cad\u0c9f\u0ca8\u0cc6 \u0ca4\u0caa\u0ccd\u0caa\u0cc1: \u0cb8\u0c82\u0cb8\u0ca6 \u0cac\u0cbf\u0c8e\u0ca8\u0ccd \u0cac\u0c9a\u0ccd\u0c9a\u0cc7\u0c97\u0ccc\u0ca1 \u0c95\u0cbf\u0ca1\u0cbf ","content":"<p><strong>\u0c9a\u0cbf\u0c95\u0ccd\u0c95\u0cac\u0cb3\u0ccd\u0cb3\u0cbe\u0caa\u0cc1\u0cb0:<\/strong> \u0cae\u0cbe\u0c9c\u0cbf \u0cb8\u0c9a\u0cbf\u0cb5, \u0c95\u0cbe\u0c82\u0c97\u0ccd\u0cb0\u0cc6\u0cb8\u0ccd \u0cb6\u0cbe\u0cb8\u0c95 \u0ca1\u0cbf\u0c95\u0cc6 \u0cb6\u0cbf\u0cb5\u0c95\u0cc1\u0cae\u0cbe\u0cb0\u0ccd \u0cac\u0cc6\u0c82\u0cac\u0cb2\u0cbf\u0cb8\u0cbf \u0c92\u0c95\u0ccd\u0c95\u0cb2\u0cbf\u0c97\u0cb0\u0cc1 \u0caa\u0ccd\u0cb0\u0ca4\u0cbf\u0cad\u0c9f\u0ca8\u0cc6 \u0ca8\u0ca1\u0cc6\u0cb8\u0cbf\u0cb0\u0cc1\u0cb5\u0cc1\u0ca6\u0cc1 \u0ca4\u0caa\u0ccd\u0caa\u0cc1. \u0c87\u0ca4\u0c82\u0cb9 \u0cb5\u0cbf\u0cb7\u0caf\u0ca6\u0cb2\u0ccd\u0cb2\u0cbf \u0c9c\u0cbe\u0ca4\u0cbf, \u0cb8\u0cae\u0cc1\u0ca6\u0cbe\u0caf\u0ca6 \u0ca8\u0ca1\u0cc1\u0cb5\u0cc6 \u0c97\u0cca\u0c82\u0ca6\u0cb2 \u0cae\u0cbe\u0ca1\u0cac\u0cbe\u0cb0\u0ca6\u0cc1 \u0c8e\u0c82\u0ca6\u0cc1 \u0cb8\u0c82\u0cb8\u0ca6 \u0cac\u0cbf\u0c8e\u0ca8\u0ccd \u0cac\u0c9a\u0ccd\u0c9a\u0cc7\u0c97\u0ccc\u0ca1 \u0cb9\u0cc7\u0cb3\u0cbf\u0ca6\u0ccd\u0ca6\u0cbe\u0cb0\u0cc6.<\/p>\n<p>\u0cac\u0cbf\u0c9c\u0cc6\u0caa\u0cbf \u0ca6\u0ccd\u0cb5\u0cc7\u0cb7\u0ca6 \u0cb0\u0cbe\u0c9c\u0c95\u0cbe\u0cb0\u0ca3 \u0cae\u0cbe\u0ca1\u0cc1\u0cb5\u0cc1\u0ca6\u0cbf\u0cb2\u0ccd\u0cb2. \u0c85\u0cb5\u0cb0\u0cb5\u0cb0\u0cc1 \u0cae\u0cbe\u0ca1\u0cbf\u0ca6\u0ccd\u0ca6\u0cc1 \u0c85\u0cb5\u0cb0\u0cc1 \u0c85\u0cad\u0cbf\u0ca8\u0cc1\u0cad\u0cb5\u0cbf\u0cb8\u0cc1\u0ca4\u0ccd\u0ca4\u0cbe\u0cb0\u0cc6. \u0cb8\u0cc1\u0cae\u0ccd\u0cae\u0ca8\u0cc6 \u0c8e\u0cb2\u0ccd\u0cb2\u0ca6\u0ccd\u0ca6\u0c95\u0ccd\u0c95\u0cc2 \u0cb0\u0cbe\u0c9c\u0c95\u0cc0\u0caf \u0cac\u0ca3\u0ccd\u0ca3 \u0cb9\u0c9a\u0ccd\u0c9a\u0cac\u0cbe\u0cb0\u0ca6\u0cc1. \u0c92\u0c95\u0ccd\u0c95\u0cb2\u0cbf\u0c97\u0cb0 \u0caa\u0ccd\u0cb0\u0ca4\u0cbf\u0cad\u0c9f\u0ca8\u0cc6 \u0c95\u0cbe\u0c82\u0c97\u0ccd\u0cb0\u0cc6\u0cb8\u0ccd \u0c97\u0cc6 \u0cb8\u0cc0\u0cae\u0cbf\u0ca4\u0cb5\u0cbe\u0c97\u0cbf\u0cb0\u0cc1\u0cb5 \u0caa\u0ccd\u0cb0\u0ca4\u0cbf\u0cad\u0c9f\u0ca8\u0cc6, \u0c85\u0ca6\u0c95\u0ccd\u0c95\u0cc2 \u0cac\u0cbf\u0c9c\u0cc6\u0caa\u0cbf\u0c97\u0cc2 \u0cb8\u0c82\u0cac\u0c82\u0ca7\u0cb5\u0cbf\u0cb2\u0ccd\u0cb2. \u0ca6\u0cc7\u0cb6\u0ca6\u0cb2\u0ccd\u0cb2\u0cbf \u0cb0\u0cbe\u0c9c\u0ccd\u0caf\u0ca6\u0cb2\u0ccd\u0cb2\u0cbf \u0c8e\u0cb2\u0ccd\u0cb2\u0cb0\u0cc2 \u0cac\u0cc7\u0c95\u0cbe\u0ca6\u0cb0\u0cc6 \u0cb0\u0cbe\u0c9c\u0c95\u0cbe\u0cb0\u0ca3 \u0cae\u0cbe\u0ca1\u0cac\u0cc7\u0c95\u0cc1. \u0c85\u0ca6\u0cc1 \u0cac\u0cbf\u0c9f\u0ccd\u0c9f\u0cc1 \u0c92\u0c95\u0ccd\u0c95\u0cb2\u0cbf\u0c97\u0cb0\u0cbf\u0c97\u0cc6 \u0cae\u0cbe\u0ca4\u0ccd\u0cb0 \u0cb8\u0cc0\u0cae\u0ca4\u0c97\u0cca\u0cb3\u0cbf\u0ca6\u0cb0\u0cc6 \u0c89\u0cb3\u0cbf\u0ca6\u0cb5\u0cb0\u0cc1 \u0cac\u0cc7\u0ca1\u0cb5\u0cc6? \u0c9c\u0cbe\u0ca4\u0cbf, \u0cb8\u0cae\u0cc1\u0ca6\u0cbe\u0caf\u0ca6 \u0ca8\u0ca1\u0cc1\u0cb5\u0cc6 \u0cb0\u0cbe\u0c9c\u0c95\u0cc0\u0caf \u0cae\u0cbe\u0ca1\u0cc1\u0cb5\u0cc1\u0ca6\u0cc1 \u0c8e\u0cb7\u0ccd\u0c9f\u0cc1 \u0cb8\u0cb0\u0cbf \u0c8e\u0c82\u0ca6\u0cc1 \u0caa\u0ccd\u0cb0\u0cb6\u0ccd\u0ca8\u0cbf\u0cb8\u0cbf\u0ca6\u0cb0\u0cc1.<\/p>","date":"2019-09-11 02:38:36","pin":"0","status":"1"},{"title":"\u0c92\u0c95\u0ccd\u0c95\u0cb2\u0cbf\u0c97 \u0cb8\u0cae\u0cc1\u0ca6\u0cbe\u0caf\u0c95\u0ccd\u0c95\u0cc6 \u0c86\u0ca6\u0cb0\u0ccd\u0cb6\u0cb5\u0cbe\u0c97\u0cac\u0cc7\u0c95\u0cbe\u0ca6\u0cb5\u0cb0\u0cc1 \u0caf\u0cbe\u0cb0\u0cc1..?: \u0cb8\u0c9a\u0cbf\u0cb5 \u0cb8\u0cbf.\u0c9f\u0cbf. \u0cb0\u0cb5\u0cbf \u0caa\u0ccd\u0cb0\u0cb6\u0ccd\u0ca8\u0cc6","content":"<blockquote class=\"twitter-tweet\"><p lang=\"kn\" dir=\"ltr\">\u0c92\u0c95\u0ccd\u0c95\u0cb2\u0cbf\u0c97 \u0cb8\u0cae\u0cc1\u0ca6\u0cbe\u0caf\u0c95\u0ccd\u0c95\u0cc6 \u0c86\u0ca6\u0cb0\u0ccd\u0cb6\u0cb5\u0cbe\u0c97\u0cac\u0cc7\u0c95\u0cbe\u0ca6\u0cb5\u0cb0\u0cc1 \u0caf\u0cbe\u0cb0\u0cc1..?: \u0cb8\u0c9a\u0cbf\u0cb5 \u0cb8\u0cbf \u0c9f\u0cbf \u0cb0\u0cb5\u0cbf \u0caa\u0ccd\u0cb0\u0cb6\u0ccd\u0ca8\u0cc6<br>  <a href=\"https:\/\/t.co\/XZ1C4Vd0rs\">https:\/\/t.co\/XZ1C4Vd0rs<\/a> via <a href=\"https:\/\/twitter.com\/KannadaPrabha?ref_src=twsrc%5Etfw\">@KannadaPrabha<\/a><a href=\"https:\/\/twitter.com\/hashtag\/CTRavi?src=hash&ref_src=twsrc%5Etfw\">#CTRavi<\/a> <a href=\"https:\/\/twitter.com\/hashtag\/OkkaligaCommunity?src=hash&ref_src=twsrc%5Etfw\">#OkkaligaCommunity<\/a> <a href=\"https:\/\/twitter.com\/hashtag\/Protest?src=hash&ref_src=twsrc%5Etfw\">#Protest<\/a><\/p>\u2014 kannadaprabha (@KannadaPrabha) <a href=\"https:\/\/twitter.com\/KannadaPrabha\/status\/1171734551699185664?ref_src=twsrc%5Etfw\">September 11, 2019<\/a><\/blockquote> <script async src=\"https:\/\/platform.twitter.com\/widgets.js\" charset=\"utf-8\"><\/script>","date":"2019-09-11 04:32:11","pin":"0","status":"1"},{"title":"\u0ca1\u0cbf\u0c95\u0cc6\u0cb6\u0cbf\u0c97\u0cc6 \u0cac\u0cc3\u0cb9\u0ca4\u0ccd \u0cac\u0cc6\u0c82\u0cac\u0cb2: \u0c92\u0c95\u0ccd\u0c95\u0cb2\u0cbf\u0c97\u0cb0\u0cc1 \u0c87\u0ca8\u0ccd\u0ca8\u0cc2 \u0c8e\u0ca6\u0ccd\u0ca6\u0cbf\u0cb2\u0ccd\u0cb2, \u0c87\u0ca6\u0cc1 \u0cb8\u0ccd\u0caf\u0cbe\u0c82\u0caa\u0cb2\u0ccd \u0c85\u0cb7\u0ccd\u0c9f\u0cc7; \u0ca8\u0c82\u0c9c\u0cbe\u0cb5\u0ca7\u0cc2\u0ca4 \u0cb8\u0ccd\u0cb5\u0cbe\u0cae\u0cc0\u0c9c\u0cbf!","content":"<p><span style=\"color: rgb(136, 153, 166); font-family: \"Helvetica Neue\", sans-serif; text-align: center; white-space: nowrap; background-color: rgb(225, 232, 237);\"><blockquote class=\"twitter-tweet\"><p lang=\"kn\" dir=\"ltr\">\u0ca1\u0cbf\u0c95\u0cc6\u0cb6\u0cbf\u0c97\u0cc6 \u0cac\u0cc3\u0cb9\u0ca4\u0ccd \u0cac\u0cc6\u0c82\u0cac\u0cb2: \u0c92\u0c95\u0ccd\u0c95\u0cb2\u0cbf\u0c97\u0cb0\u0cc1 \u0c87\u0ca8\u0ccd\u0ca8\u0cc2 \u0c8e\u0ca6\u0ccd\u0ca6\u0cbf\u0cb2\u0ccd\u0cb2, \u0c87\u0ca6\u0cc1 \u0cb8\u0ccd\u0caf\u0cbe\u0c82\u0caa\u0cb2\u0ccd \u0c85\u0cb7\u0ccd\u0c9f\u0cc7; \u0ca8\u0c82\u0c9c\u0cbe\u0cb5\u0ca7\u0cc2\u0ca4 \u0cb8\u0ccd\u0cb5\u0cbe\u0cae\u0cc0\u0c9c\u0cbf! <a href=\"https:\/\/t.co\/dmmuZ7evLh\">https:\/\/t.co\/dmmuZ7evLh<\/a><\/p>&mdash; kannadaprabha (@KannadaPrabha) <a href=\"https:\/\/twitter.com\/KannadaPrabha\/status\/1171774100705906688?ref_src=twsrc%5Etfw\">September 11, 2019<\/a><\/blockquote> <script async src=\"https:\/\/platform.twitter.com\/widgets.js\" charset=\"utf-8\"><\/script><\/span><\/p>","date":"2019-09-11 06:50:33","pin":"0","status":"0"},{"title":"\u0ca1\u0cbf\u0c95\u0cc6\u0cb6\u0cbf\u0c97\u0cc6 \u0cac\u0cc3\u0cb9\u0ca4\u0ccd \u0cac\u0cc6\u0c82\u0cac\u0cb2: \u0c92\u0c95\u0ccd\u0c95\u0cb2\u0cbf\u0c97\u0cb0\u0cc1 \u0c87\u0ca8\u0ccd\u0ca8\u0cc2 \u0c8e\u0ca6\u0ccd\u0ca6\u0cbf\u0cb2\u0ccd\u0cb2, \u0c87\u0ca6\u0cc1 \u0cb8\u0ccd\u0caf\u0cbe\u0c82\u0caa\u0cb2\u0ccd \u0c85\u0cb7\u0ccd\u0c9f\u0cc7; \u0ca8\u0c82\u0c9c\u0cbe\u0cb5\u0ca7\u0cc2\u0ca4 \u0cb8\u0ccd\u0cb5\u0cbe\u0cae\u0cc0\u0c9c\u0cbf!","content":"<blockquote class=\"twitter-tweet\"><p lang=\"kn\" dir=\"ltr\">\u0ca1\u0cbf\u0c95\u0cc6\u0cb6\u0cbf\u0c97\u0cc6 \u0cac\u0cc3\u0cb9\u0ca4\u0ccd \u0cac\u0cc6\u0c82\u0cac\u0cb2: \u0c92\u0c95\u0ccd\u0c95\u0cb2\u0cbf\u0c97\u0cb0\u0cc1 \u0c87\u0ca8\u0ccd\u0ca8\u0cc2 \u0c8e\u0ca6\u0ccd\u0ca6\u0cbf\u0cb2\u0ccd\u0cb2, \u0c87\u0ca6\u0cc1 \u0cb8\u0ccd\u0caf\u0cbe\u0c82\u0caa\u0cb2\u0ccd \u0c85\u0cb7\u0ccd\u0c9f\u0cc7; \u0ca8\u0c82\u0c9c\u0cbe\u0cb5\u0ca7\u0cc2\u0ca4 \u0cb8\u0ccd\u0cb5\u0cbe\u0cae\u0cc0\u0c9c\u0cbf! <a href=\"https:\/\/t.co\/dmmuZ7evLh\">https:\/\/t.co\/dmmuZ7evLh<\/a><\/p>\u2014 kannadaprabha (@KannadaPrabha) <a href=\"https:\/\/twitter.com\/KannadaPrabha\/status\/1171774100705906688?ref_src=twsrc%5Etfw\">September 11, 2019<\/a><\/blockquote> <script async src=\"https:\/\/platform.twitter.com\/widgets.js\" charset=\"utf-8\"><\/script>","date":"2019-09-11 06:51:53","pin":"0","status":"1"}]}